vscode_cli_helpers/__init__.py
vscode_cli_helpers/open_file/__init__.py
vscode_cli_helpers/open_file/config.py
vscode_cli_helpers/open_file/data/default_config.ini
vscode_cli_helpers/open_file/data/templates/C++.txt
vscode_cli_helpers/open_file/data/templates/Python.txt
vscode_cli_helpers/open_file/exceptions.py
vscode_cli_helpers/open_file/open_file.py
vscode_cli_helpers/open_file/script.py
vscode_cli_helpers_open_file-0.1.13.dist-info/LICENSE
vscode_cli_helpers_open_file-0.1.13.dist-info/METADATA
vscode_cli_helpers_open_file-0.1.13.dist-info/WHEEL
vscode_cli_helpers_open_file-0.1.13.dist-info/entry_points.txt
vscode_cli_helpers_open_file-0.1.13.dist-info/RECORD
